provival/provival.py
provival/data/SC_DB_Human.pickle
provival/data/SC_DB_Metadata.pickle
provival/data/SC_DB_Mouse.pickle
provival-0.0.2.dist-info/METADATA
provival-0.0.2.dist-info/WHEEL
provival-0.0.2.dist-info/top_level.txt
provival-0.0.2.dist-info/RECORD
