Metadata-Version: 2.1
Name: provival
Version: 0.0.2
Summary: Provival
Home-page: https://github.com/davidchen0420
Author: David Chen
Author-email: davidc.chen@mail.utoronto.ca
License: BSD 2-clause
Classifier: Development Status :: 1 - Planning
Classifier: Intended Audience :: Science/Research
Classifier: License :: OSI Approved :: BSD License
Classifier: Operating System :: POSIX :: Linux
Classifier: Programming Language :: Python :: 3
Requires-Dist: decoupler >=1.8.0
Requires-Dist: pandas >=2.2.3
Requires-Dist: scipy >=1.14.1
